{
  "doctor": [
    {
      "id": "6e448eee-3baf-43d1-8cd8-e457cb6eb4ea",
      "departmentId": "b37a48dd-8f84-4dbc-ae75-b813f4a37450",
      "link": "https://www.doctorbangladesh.com/dr-md-khalilur-rahman/",
      "imageId": "870d8bf5-c6b2-4324-91cb-ff538756ec16",
      "name": "Dr. Md. Khalilur Rahman",
      "degree": "MBBS (RMC), DTCD (DMC), Trained (Thailand, Tanzania)",
      "specialty": "Chest & TB Diseases Specialist",
      "workplace": "Chest Disease Clinic & Hospital, Pabna",
      "info": "Dr. Md. Khalilur Rahman is a Chest Diseases Specialist in Pabna. His qualification is MBBS (RMC), DTCD (DMC), Trained (Thailand, Tanzania). He is working as a Chest & TB Diseases Specialist doctor in Chest Disease Clinic & Hospital, Pabna. He regularly provides treatment to his patients at Sunrise Diagnostic Center, Pabna. Practicing hour of Dr. Md. Khalilur Rahman at Sunrise Diagnostic Center, Pabna is 9am to 1pm & 5pm to 8pm (Everyday).",
      "chamber": {
        "hospital": "Sunrise Diagnostic Center, Pabna",
        "address": "In front pf TB Hospital, Hospital Road, Shalgaria, Pabna",
        "visitingTime": "9am to 1pm & 5pm to 8pm (Everyday)",
        "appointmentNumber": "+8801733976442Call Now"
      }
    },
    {
      "id": "42760daa-bca4-4f36-9d56-40499ebccc06",
      "departmentId": "b37a48dd-8f84-4dbc-ae75-b813f4a37450",
      "link": "https://www.doctorbangladesh.com/dr-md-moklesur-rahman/",
      "imageId": "b84b0ce3-8355-4ff4-b818-ff348112dec8",
      "name": "Dr. Md. Moklesur Rahman",
      "degree": "MBBS, BCS (Health), DTCD (NIDCH)",
      "specialty": "Chest Diseases, Asthma & Respiratory Medicine Specialist",
      "workplace": "Chest Disease Clinic & Hospital, Pabna",
      "info": "Dr. Md. Moklesur Rahman is a Chest Diseases Specialist in Pabna. His qualification is MBBS, BCS (Health), DTCD (NIDCH). He is a Jr. Consultant (Respiratory Medicine) at Chest Disease Clinic & Hospital, Pabna. He regularly provides treatment to his patients at Labaid Diagnostic, Pabna. Practicing hour of Dr. Md. Moklesur Rahman at Labaid Diagnostic, Pabna is 5pm to 9pm (Closed: Friday).",
      "chamber": {
        "hospital": "Labaid Diagnostic, Pabna",
        "address": "Beside Joy Kali Bari, Thana Road, Shalgaria, Pabna",
        "visitingTime": "5pm to 9pm (Closed: Friday)",
        "appointmentNumber": "+8801766661901Call Now"
      }
    },
    {
      "id": "e2986b8d-462b-4e46-ac95-1f8951115408",
      "departmentId": "b37a48dd-8f84-4dbc-ae75-b813f4a37450",
      "link": "https://www.doctorbangladesh.com/dr-shis-mohammad-sarkar/",
      "imageId": "fbad281e-b99a-4be9-8e1d-04bfceff0712",
      "name": "Dr. Shish Mohammad Sarkar",
      "degree": "MBBS, BCS (Health), FCPS (Medicine), MD (Chest Diseases)",
      "specialty": "Chest Diseases, Asthma & Medicine Specialist",
      "workplace": "Rajshahi Medical College & Hospital",
      "info": "Kimia Diagnostic Center, Pabna Address: Pach Matha Mor, Beside Central Girls School, Shalgaria, Pabna Visiting Hour: 9am to 5pm (Only Friday) Appointment: +8801711489711 Call Now",
      "chamber": {
        "hospital": "Popular Diagnostic Center, Rajshahi",
        "address": "House # 474, Chowdhury Tower, Laxmipur, Rajshahi",
        "visitingTime": "5:30pm to 8pm (Closed: Friday & Saturday)",
        "appointmentNumber": "+8809666787811Call Now"
      }
    },
    {
      "id": "9cf4d4af-bda4-4122-8b13-6d79f20adea9",
      "departmentId": "b37a48dd-8f84-4dbc-ae75-b813f4a37450",
      "link": "https://www.doctorbangladesh.com/dr-md-sanwar-newaz-khan/",
      "imageId": "17b986ae-0375-4fe7-8b71-f11293ecac57",
      "name": "Dr. Md. Sanwar Nawaz Khan",
      "degree": "MBBS (Dhaka), BCS (Health), MD (Chest Diseases)",
      "specialty": "Chest Diseases (Asthma, Cough, COPD) & Respiratory Medicine Specialist",
      "workplace": "Chest Disease Clinic & Hospital, Pabna",
      "info": "Dr. Md. Sanwar Nawaz Khan is a Chest Diseases Specialist in Pabna. His qualification is MBBS (Dhaka), BCS (Health), MD (Chest Diseases). He is a Consultant, Chest Diseases at Chest Disease Clinic & Hospital, Pabna. He regularly provides treatment to his patients at Shimla Hospital, Pabna. Practicing hour of Dr. Md. Sanwar Nawaz Khan at Shimla Hospital, Pabna is 4pm to 9pm (Sat to Thu) & 9am to 4pm (Friday).",
      "chamber": {
        "hospital": "Shimla Hospital, Pabna",
        "address": "Shimla Tower, Thana Mor, Hospital Road, Pabna",
        "visitingTime": "4pm to 9pm (Sat to Thu) & 9am to 4pm (Friday)",
        "appointmentNumber": "+8801713228218Call Now"
      }
    }
  ]
}