{
  "doctor": [
    {
      "name": "Dr. Chaya Bhattacharjee",
      "degree": "M.Sc (Psychology), M.Phil (Psychology), Ph.D (Psychology)",
      "specialty": "Psychologist & Therapeutic Counselor",
      "workplace": "Labaid Specialized Hospital, Dhanmondi",
      "info": "Dr. Chaya Bhattacharjee is a Psychologist in Dhaka. Her qualification is M.Sc (Psychology), M.Phil (Psychology), Ph.D (Psychology). She is a Consultant, Psychology at Labaid Specialized Hospital, Dhanmondi. She regularly provides treatment to her patients at Labaid Specialized Hospital, Dhanmondi. Practicing hour of Dr. Chaya Bhattacharjee at Labaid Specialized Hospital, Dhanmondi is 10am to 4pm (Closed: Friday).",
      "chamber": {
        "hospital": "Labaid Specialized Hospital, Dhanmondi",
        "address": "House # 06, Road # 04, Dhanmondi, Dhaka - 1205",
        "visitingTime": "10am to 4pm (Closed: Friday)",
        "appointmentNumber": "10606Call Now"
      }
    },
    {
      "name": "Selina Fatema Binte Shahid",
      "degree": "B.Sc (Psychology), M.Sc (Clinical Psychology), M.Phil (Clinical Psychology)",
      "specialty": "Clinical Psychologist & Psychotherapist",
      "workplace": "Bangabandhu Sheikh Mujib Medical University Hospital",
      "info": "Selina Fatema Binte Shahid is a Psychologist in Dhaka. Her qualification is B.Sc (Psychology), M.Sc (Clinical Psychology), M.Phil (Clinical Psychology). She is a Assistant Professor, Clinical Psychology at Bangabandhu Sheikh Mujib Medical University Hospital. She regularly provides treatment to her patients at Bangladesh Psychiatric Care. Practicing hour of Selina Fatema Binte Shahid at Bangladesh Psychiatric Care is 3.30pm to 8.30pm (Closed: Friday).",
      "chamber": {
        "hospital": "Bangladesh Psychiatric Care",
        "address": "Suit # 6020, Shimanto Shambhar (6th Floor), Dhanmondi, Dhaka",
        "visitingTime": "3.30pm to 8.30pm (Closed: Friday)",
        "appointmentNumber": "+8801872863002Call Now"
      }
    }
  ]
}