{
  "doctor": [
    {
      "id": "8b8feb39-54d6-41b8-8225-310dcb3edc4e",
      "departmentId": "5dc2834f-fe68-46c4-a68f-f138e11116b6",
      "link": "https://www.doctorbangladesh.com/dr-arman-uddin-ahmad/",
      "imageId": "6b09f1e5-7b80-4ca0-ac6a-a04c134f6f66",
      "name": "Dr. Arman Uddin Ahmad",
      "degree": "MBBS, FCPS (EYE), MS (EYE)",
      "specialty": "Eye Diseases Specialist & Phaco Surgeon",
      "workplace": "Kushtia Medical College & Hospital",
      "info": "Dr. Arman Uddin Ahmad is a Eye Specialist in Kushtia. His qualification is MBBS, FCPS (EYE), MS (EYE). He is a Assistant Professor, Eye at Kushtia Medical College & Hospital. He regularly provides treatment to his patients at Sono Consultation Center, Kushtia. Practicing hour of Dr. Arman Uddin Ahmad at Sono Consultation Center, Kushtia is 5pm to 8pm (Sat, Mon, Wed).",
      "chamber": {
        "hospital": "Sono Consultation Center, Kushtia",
        "address": "Sono Tower 2, Court Para, Kushtia, Bangladesh",
        "visitingTime": "5pm to 8pm (Sat, Mon, Wed)",
        "appointmentNumber": "+8801770997352Call Now"
      }
    },
    {
      "id": "6dd58fa8-d2d9-40f8-a636-3c9c03e00476",
      "departmentId": "5dc2834f-fe68-46c4-a68f-f138e11116b6",
      "link": "https://www.doctorbangladesh.com/dr-kazi-anisur-rahman/",
      "imageId": "549e80a4-f349-44d1-a5cb-a8997084aff0",
      "name": "Dr. Kazi Anisur Rahman",
      "degree": "MBBS, BCS (Health), MS (EYE)",
      "specialty": "Eye Diseases Specialist, Phaco & Micro Surgeon",
      "workplace": "Kushtia Medical College & Hospital",
      "info": "Dr. Kazi Anisur Rahman is a Eye Specialist in Kushtia. His qualification is MBBS, BCS (Health), MS (EYE). He is a Assistant Professor, Eye at Kushtia Medical College & Hospital. He regularly provides treatment to his patients at Sono Diagnostic Center, Kushtia. Practicing hour of Dr. Kazi Anisur Rahman at Sono Diagnostic Center, Kushtia is 4pm to 7pm (Sat, Sun, Tue & Wed), 8am to 1pm (Fri).",
      "chamber": {
        "hospital": "Sono Diagnostic Center, Kushtia",
        "address": "Sono Tower, College Mor, Court Para, Kushtia",
        "visitingTime": "4pm to 7pm (Sat, Sun, Tue & Wed), 8am to 1pm (Fri)",
        "appointmentNumber": "+8801745836325Call Now"
      }
    }
  ]
}